MANIFEST.in
README.rst
pyproject.toml
setup.py
src/zombiedice/__init__.py
src/zombiedice/__main__.py
src/zombiedice/examples.py
src/zombiedice/imgTitle.png
src/zombiedice/imgZombieCheerleader.jpg
src/zombiedice/jquery-1.8.3.min.js
src/zombiedice.egg-info/PKG-INFO
src/zombiedice.egg-info/SOURCES.txt
src/zombiedice.egg-info/dependency_links.txt
src/zombiedice.egg-info/top_level.txt