Metadata-Version: 1.1
Name: zombiedice
Version: 0.1.6
Summary: A simulator for the dice game Zombie Dice that can run bot AI players.
Home-page: https://github.com/asweigart/zombiedice
Author: Al Sweigart
Author-email: al@inventwithpython.com
License: BSD
Keywords: zombie dice game ai simulator bots
Platform: UNKNOWN
Classifier: Development Status :: 4 - Beta
Classifier: Intended Audience :: Developers
Classifier: License :: OSI Approved :: BSD License
Classifier: Operating System :: OS Independent
Classifier: Programming Language :: Python
Classifier: Programming Language :: Python :: 3
Classifier: Programming Language :: Python :: 3.1
Classifier: Programming Language :: Python :: 3.2
Classifier: Programming Language :: Python :: 3.3
Classifier: Programming Language :: Python :: 3.4
Classifier: Programming Language :: Python :: 3.5
Classifier: Programming Language :: Python :: 3.6
Classifier: Programming Language :: Python :: 3.7
Classifier: Programming Language :: Python :: 3.8
Classifier: Programming Language :: Python :: 3.9
